pygoogleanalytics/__init__.py
pygoogleanalytics/_version.py
pygoogleanalytics/api_caller.py
pygoogleanalytics/dataflow.py
pygoogleanalytics/request_filter.py
pygoogleanalytics/requester.py
pygoogleanalytics/segment.py
pygoogleanalytics/segment_filter.py
pygoogleanalytics-1.1.dist-info/DESCRIPTION.rst
pygoogleanalytics-1.1.dist-info/METADATA
pygoogleanalytics-1.1.dist-info/RECORD
pygoogleanalytics-1.1.dist-info/WHEEL
pygoogleanalytics-1.1.dist-info/metadata.json
pygoogleanalytics-1.1.dist-info/top_level.txt
