Metadata-Version: 1.0
Name: pygoogleanalytics
Version: 1.1
Summary: Wrapper for Google Analytics API python call
Home-page: https://github.com/ademilly/pygoogleanalytics
Author: Aurélien Demilly
Author-email: demilly.aurelien@gmail.com
License: UNKNOWN
Keywords: data,analytics,google,python
Platform: UNKNOWN
